vegrofi/__init__.py
vegrofi/__main__.py
vegrofi/_convert.py
vegrofi-0.0.2.dist-info/licenses/LICENSE
vegrofi-0.0.2.dist-info/METADATA
vegrofi-0.0.2.dist-info/WHEEL
vegrofi-0.0.2.dist-info/entry_points.txt
vegrofi-0.0.2.dist-info/top_level.txt
vegrofi-0.0.2.dist-info/RECORD
